rr_graph/README.md
rr_graph/__init__.py
rr_graph/channel.py
rr_graph/channel2.py
rr_graph/graph.py
rr_graph/graph2.py
rr_graph/points.py
rr_graph/tracks.py
rr_graph/version.py
rr_graph/capnp/__init__.py
rr_graph/capnp/graph2.py
rr_graph/tests/__init__.py
rr_graph/tests/test_channel.py
rr_graph/tests/test_channel2.py
rr_graph/tests/test_graph.py
rr_graph/tests/test_graph2.py
rr_graph/tests/test_points.py
rr_graph/tests/test_tracks.py
rr_graph/utils/__init__.py
rr_graph/utils/asserts.py
rr_graph/utils/collections_extra.py
rr_graph/utils/progressbar_utils.py
rr_graph/xml/__init__.py
rr_graph/xml/graph2.py
rr_graph/xml/utils.py
rr_graph-0.0.1.post22.dist-info/LICENSE
rr_graph-0.0.1.post22.dist-info/METADATA
rr_graph-0.0.1.post22.dist-info/WHEEL
rr_graph-0.0.1.post22.dist-info/top_level.txt
rr_graph-0.0.1.post22.dist-info/RECORD
